CSE-3108/lab02/Adder1bit.v
module Adder1bit (
    input A,
    input B,
    input Cin,
    output S,
    output Cout
);

assign S = A ^ B ^ Cin;
assign Cout = (A & B) | (A ^ B) & Cin;
    
endmodule

CSE-3108/lab02/Adder4bit_tb.v
`timescale 1ns/1ps
module Adder1bit_tb;

    // Inputs
    reg A;
    reg B;
    reg Cin;

    // Outputs
    wire S;
    wire Cout;

    // Instantiate the Unit Under Test (UUT)
    Adder1bit uut (A, B, Cin, S, Cout);

    initial begin

        $dumpfile("Adder4bit_tb_test.vcd");
        $dumpvars(0, Adder1bit_tb);


        // Initialize Inputs
        A = 1'b0;
        B = 1'b0;
        Cin = 1'b0;

        #20
        A = 1'b0;
        B = 1'b0;
        Cin = 1'b1;

        #20
        A = 1'b0;
        B = 1'b1;
        Cin = 1'b0;

        #20
        A = 1'b0;
        B = 1'b1;
        Cin = 1'b1;

        #20
        A = 1'b1;
        B = 1'b0;
        Cin = 1'b0;

        #20
        A = 1'b1;
        B = 1'b0;
        Cin = 1'b1;

        #20
        A = 1'b1;
        B = 1'b1;
        Cin = 1'b0;

        #20
        A = 1'b1;
        B = 1'b1;
        Cin = 1'b1;

        #20
        $finish;
    end

    initial begin
        $monitor("A=%b, B=%b, Cin=%b, S=%b, Cout=%b\n", A, B, Cin, S, Cout);
    end

endmodule

CSE-3108/lab02/Adder1bit_tb_test.vcd
$date
	Sat May  4 12:06:45 2024
$end
$version
	Icarus Verilog
$end
$timescale
	1ps
$end
$scope module Adder1bit_tb $end
$var wire 1 ! S $end
$var wire 1 " Cout $end
$var reg 1 # A $end
$var reg 1 $ B $end
$var reg 1 % Cin $end
$scope module uut $end
$var wire 1 # A $end
$var wire 1 $ B $end
$var wire 1 % Cin $end
$var wire 1 " Cout $end
$var wire 1 ! S $end
$upscope $end
$upscope $end
$enddefinitions $end
$comment Show the parameter values. $end
$dumpall
$end
#0
$dumpvars
0%
0$
0#
0"
0!
$end
#20000
1!
1%
#40000
0%
1$
#60000
1"
0!
1%
#80000
0"
1!
0%
0$
1#
#100000
1"
0!
1%
#120000
0%
1$
#140000
1!
1%
